tensorcircuit/__init__.py
tensorcircuit/asciiart.py
tensorcircuit/backend.py
tensorcircuit/channels.py
tensorcircuit/circuit.py
tensorcircuit/cons.py
tensorcircuit/densitymatrix.py
tensorcircuit/densitymatrix2.py
tensorcircuit/experimental.py
tensorcircuit/gates.py
tensorcircuit/interfaces.py
tensorcircuit/keras.py
tensorcircuit/mps_base.py
tensorcircuit/mpscircuit.py
tensorcircuit/quantum.py
tensorcircuit/simplify.py
tensorcircuit/torchnn.py
tensorcircuit/translation.py
tensorcircuit/utils.py
tensorcircuit/vis.py
tensorcircuit/applications/__init__.py
tensorcircuit/applications/dqas.py
tensorcircuit/applications/graphdata.py
tensorcircuit/applications/layers.py
tensorcircuit/applications/utils.py
tensorcircuit/applications/vags.py
tensorcircuit/applications/van.py
tensorcircuit/applications/vqes.py
tensorcircuit/backends/__init__.py
tensorcircuit/backends/abstract_backend.py
tensorcircuit/backends/backend_factory.py
tensorcircuit/backends/jax_backend.py
tensorcircuit/backends/jax_ops.py
tensorcircuit/backends/numpy_backend.py
tensorcircuit/backends/pytorch_backend.py
tensorcircuit/backends/pytorch_ops.py
tensorcircuit/backends/tensorflow_backend.py
tensorcircuit/backends/tf_ops.py
tensorcircuit/interfaces/__init__.py
tensorcircuit/interfaces/scipy.py
tensorcircuit/interfaces/tensorflow.py
tensorcircuit/interfaces/tensortrans.py
tensorcircuit/interfaces/torch.py
tensorcircuit/templates/__init__.py
tensorcircuit/templates/blocks.py
tensorcircuit/templates/chems.py
tensorcircuit/templates/dataset.py
tensorcircuit/templates/graphs.py
tensorcircuit/templates/measurements.py
tests/__init__.py
tests/conftest.py
tests/test_backends.py
tests/test_circuit.py
tests/test_dmcircuit.py
tests/test_gates.py
tests/test_interfaces.py
tests/test_keras.py
tests/test_miscs.py
tests/test_mpscircuit.py
tests/test_qaoa.py
tests/test_quantum.py
tests/test_quantum_attr.py
tests/test_simplify.py
tests/test_templates.py
tests/test_torchnn.py
tests/test_van.py
tensorcircuitx-0.2.2.dev20220706.dist-info/LICENSE
tensorcircuitx-0.2.2.dev20220706.dist-info/METADATA
tensorcircuitx-0.2.2.dev20220706.dist-info/WHEEL
tensorcircuitx-0.2.2.dev20220706.dist-info/top_level.txt
tensorcircuitx-0.2.2.dev20220706.dist-info/RECORD
