Metadata-Version: 2.1
Name: tensorcircuitx
Version: 0.2.2.dev20220706
Summary: packagename placeholder
Home-page: https://github.com/refraction-ray/tensorcircuit-dev
Author: TensorCircuit Authors
Author-email: znfesnpbh.tc@gmail.com
License: UNKNOWN
Platform: UNKNOWN
Classifier: Programming Language :: Python :: 3
Classifier: Operating System :: OS Independent
License-File: LICENSE
Requires-Dist: numpy
Requires-Dist: scipy
Requires-Dist: tensornetwork
Requires-Dist: networkx
Requires-Dist: tensorflow
